syspro/__init__.py
syspro/client.py
syspro/errors.py
syspro/utils.py
syspro/models/__init__.py
syspro/models/base.py
syspro/models/contract.py
syspro/models/ecc.py
syspro/models/purchaseorder.py
syspro/models/requisition.py
syspro/models/stockcode.py
syspro/models/table.py
syspro_sdk-0.1.33.dist-info/licenses/LICENSE
syspro_sdk-0.1.33.dist-info/METADATA
syspro_sdk-0.1.33.dist-info/WHEEL
syspro_sdk-0.1.33.dist-info/top_level.txt
syspro_sdk-0.1.33.dist-info/RECORD
