Metadata-Version: 2.4
Name: syspro-sdk
Version: 0.1.33
Summary: A python SDK for Syspro
Author: Vincent Goineau
Author-email: Vincent Goineau <vincent@heyvince.co>
Requires-Python: >=3.8
License-File: LICENSE
Requires-Dist: httpx==0.28.1
Requires-Dist: xmltodict==0.14.2
Requires-Dist: jsonpath-ng==1.7.0
Requires-Dist: jsonpath-ng==1.7.0
Requires-Dist: numpy==2.2.2
Dynamic: author
Dynamic: license-file
Dynamic: requires-python
